zubbi/__init__.py
zubbi/cli.py
zubbi/default_settings.py
zubbi/doc.py
zubbi/extensions.py
zubbi/helpers.py
zubbi/models.py
zubbi/utils.py
zubbi/views.py
zubbi/scraper/__init__.py
zubbi/scraper/exceptions.py
zubbi/scraper/main.py
zubbi/scraper/repo_parser.py
zubbi/scraper/scraper.py
zubbi/scraper/tenant_parser.py
zubbi/scraper/connections/__init__.py
zubbi/scraper/connections/gerrit.py
zubbi/scraper/connections/git.py
zubbi/scraper/connections/github.py
zubbi/scraper/repos/__init__.py
zubbi/scraper/repos/gerrit.py
zubbi/scraper/repos/git.py
zubbi/scraper/repos/github.py
zubbi/static/functions.js
zubbi/static/pygments.css
zubbi/static/style.css
zubbi/static/css/bootstrap.min.css
zubbi/static/css/bootstrap.min.css.map
zubbi/static/css/fontawesome-all.min.css
zubbi/static/css/jquery-ui.min.css
zubbi/static/js/bootstrap.bundle.min.js
zubbi/static/js/bootstrap.bundle.min.js.map
zubbi/static/js/bootstrap.min.js
zubbi/static/js/bootstrap.min.js.map
zubbi/static/js/jquery-3.3.1.min.js
zubbi/static/js/jquery-ui.min.js
zubbi/static/js/typed.min.js
zubbi/static/js/typed.min.js.map
zubbi/static/webfonts/fa-brands-400.eot
zubbi/static/webfonts/fa-brands-400.svg
zubbi/static/webfonts/fa-brands-400.ttf
zubbi/static/webfonts/fa-brands-400.woff
zubbi/static/webfonts/fa-brands-400.woff2
zubbi/static/webfonts/fa-regular-400.eot
zubbi/static/webfonts/fa-regular-400.svg
zubbi/static/webfonts/fa-regular-400.ttf
zubbi/static/webfonts/fa-regular-400.woff
zubbi/static/webfonts/fa-regular-400.woff2
zubbi/static/webfonts/fa-solid-900.eot
zubbi/static/webfonts/fa-solid-900.svg
zubbi/static/webfonts/fa-solid-900.ttf
zubbi/static/webfonts/fa-solid-900.woff
zubbi/static/webfonts/fa-solid-900.woff2
zubbi/templates/_css.html
zubbi/templates/_footer.html
zubbi/templates/_js.html
zubbi/templates/_navbar.html
zubbi/templates/base.html
zubbi/templates/details.html
zubbi/templates/error.html
zubbi/templates/how-to.html
zubbi/templates/index.html
zubbi/templates/lmzify.html
zubbi-3.0.0.dist-info/METADATA
zubbi-3.0.0.dist-info/WHEEL
zubbi-3.0.0.dist-info/entry_points.txt
zubbi-3.0.0.dist-info/RECORD
