Metadata-Version: 2.4
Name: zubbi
Version: 3.0.0
Summary: Index for finding jobs & roles used in a Zuul based CI system
Project-URL: repository, https://github.com/bmwcarit/zubbi
Project-URL: Changelog, https://github.com/bmwcarit/zubbi/blob/master/CHANGELOG.md
Author-email: Felix Edel <felix.edel@bmw.de>, Simon Westphahl <simon.westphahl@bmw.de>, Benedikt Loeffler <benedikt.loeffler@bmw.de>
License-Expression: Apache-2.0
Classifier: Development Status :: 5 - Production/Stable
Classifier: Framework :: Flask
Classifier: License :: OSI Approved :: Apache Software License
Classifier: Operating System :: POSIX
Classifier: Programming Language :: Python :: 3 :: Only
Requires-Python: >=3.10
Requires-Dist: arrow
Requires-Dist: cachelib
Requires-Dist: click
Requires-Dist: cryptography
Requires-Dist: elasticsearch<10.0.0
Requires-Dist: flask
Requires-Dist: github3-py
Requires-Dist: gitpython
Requires-Dist: jinja2
Requires-Dist: markupsafe
Requires-Dist: pyjwt
Requires-Dist: pyyaml
Requires-Dist: pyzmq
Requires-Dist: readme-renderer[md]
Requires-Dist: requests
Requires-Dist: sphinx
Requires-Dist: tabulate
Requires-Dist: zuul-sphinx
